setup.py
simpleobfuscate/__init__.py
simpleobfuscate/simpleobfuscate.py
simpleobfuscate.egg-info/PKG-INFO
simpleobfuscate.egg-info/SOURCES.txt
simpleobfuscate.egg-info/dependency_links.txt
simpleobfuscate.egg-info/top_level.txt