Metadata-Version: 1.0
Name: simpleobfuscate
Version: 0.1.0
Summary: Simple, compact, randomized obfuscation for Python strings
Home-page: http://github.com/ternus/obfuscate
Author: Christian Ternus
Author-email: ternus@cternus.net
License: Creative Commons Attribution-Noncommercial-Share Alike license
Platform: UNKNOWN
